[{
	"id":"1",
	"g1":"￥98",
	"g2":"包邮",
	"g3":"春秋季休闲运动套装女2019新款时尚",
	"g4":"林晓梅",
	"g5":"16人付款",
	"g6":"如实描述：4.7",
	"src":"https://img.alicdn.com/imgextra/i4/1804006046980628855/TB2Ytk9qB8lpuFjSspaXXXJKpXa_!!0-saturn_solar.jpg_220x220.jpg_.webp"
},{
	"id":"2",
	"g1":"￥258",
	"g2":"包邮",
	"g3":"春秋季休闲运动套装女2019新款时尚",
	"g4":"林晓梅",
	"g5":"16人付款",
	"g6":"如实描述：4.7",
	"src":"https://img.alicdn.com/imgextra/i2/11149950/O1CN012KphB72NN9MVcO2yF_!!0-saturn_solar.jpg_220x220.jpg_.webp"
},{
	"id":"3",
	"g1":"￥156",
	"g2":"包邮",
	"g3":"春秋季休闲运动套装女2019新款时尚",
	"g4":"林晓梅",
	"g5":"16人付款",
	"g6":"如实描述：4.7",
	"src":"https://img.alicdn.com/imgextra/i1/130016417/O1CN01QY1Ni01xH248w42tz_!!0-saturn_solar.jpg_220x220.jpg_.webp"
},{
	"id":"4",
	"g1":"￥489",
	"g2":"包邮",
	"g3":"春秋季休闲运动套装女2019新款时尚",
	"g4":"林晓梅",
	"g5":"16人付款",
	"g6":"如实描述：4.7",
	"src":"https://img.alicdn.com/imgextra/i4/187730123/O1CN01kkm2EE1CmNE2T24PE_!!0-saturn_solar.jpg_220x220.jpg_.webp"
},{
	"id":"5",
	"g1":"￥532",
	"g2":"包邮",
	"g3":"春秋季休闲运动套装女2019新款时尚",
	"g4":"林晓梅",
	"g5":"16人付款",
	"g6":"如实描述：4.7",
	"src":"https://img.alicdn.com/imgextra/i2/11149950/O1CN012KphB72NN9MVcO2yF_!!0-saturn_solar.jpg_220x220.jpg_.webp"
},{
	"id":"6",
	"g1":"￥125",
	"g2":"包邮",
	"g3":"春秋季休闲运动套装女2019新款时尚",
	"g4":"林晓梅",
	"g5":"16人付款",
	"g6":"如实描述：4.7",
	"src":"https://img.alicdn.com/imgextra/i4/187730123/O1CN01kkm2EE1CmNE2T24PE_!!0-saturn_solar.jpg_220x220.jpg_.webp"
},{
	"id":"7",
	"g1":"￥99",
	"g2":"包邮",
	"g3":"春秋季休闲运动套装女2019新款时尚",
	"g4":"林晓梅",
	"g5":"16人付款",
	"g6":"如实描述：4.7",
	"src":"https://img.alicdn.com/imgextra/i4/1804006046980628855/TB2Ytk9qB8lpuFjSspaXXXJKpXa_!!0-saturn_solar.jpg_220x220.jpg_.webp"
},{
	"id":"8",
	"g1":"￥69",
	"g2":"包邮",
	"g3":"春秋季休闲运动套装女2019新款时尚",
	"g4":"林晓梅",
	"g5":"16人付款",
	"g6":"如实描述：4.7",
	"src":"https://img.alicdn.com/imgextra/i1/130016417/O1CN01QY1Ni01xH248w42tz_!!0-saturn_solar.jpg_220x220.jpg_.webp"
},{
	"id":"9",
	"g1":"￥135",
	"g2":"包邮",
	"g3":"春秋季休闲运动套装女2019新款时尚",
	"g4":"林晓梅",
	"g5":"16人付款",
	"g6":"如实描述：4.7",
	"src":"https://img.alicdn.com/imgextra/i1/130016417/O1CN01QY1Ni01xH248w42tz_!!0-saturn_solar.jpg_220x220.jpg_.webp"
},{
	"id":"10",
	"g1":"￥166",
	"g2":"包邮",
	"g3":"春秋季休闲运动套装女2019新款时尚",
	"g4":"林晓梅",
	"g5":"16人付款",
	"g6":"如实描述：4.7",
	"src":"https://img.alicdn.com/imgextra/i2/11149950/O1CN012KphB72NN9MVcO2yF_!!0-saturn_solar.jpg_220x220.jpg_.webp"
},{
	"id":"11",
	"g1":"￥59",
	"g2":"包邮",
	"g3":"春秋季休闲运动套装女2019新款时尚",
	"g4":"林晓梅",
	"g5":"16人付款",
	"g6":"如实描述：4.7",
	"src":"https://img.alicdn.com/imgextra/i4/187730123/O1CN01kkm2EE1CmNE2T24PE_!!0-saturn_solar.jpg_220x220.jpg_.webp"
},{
	"id":"12",
	"g1":"￥100",
	"g2":"包邮",
	"g3":"春秋季休闲运动套装女2019新款时尚",
	"g4":"林晓梅",
	"g5":"16人付款",
	"g6":"如实描述：4.7",
	"src":"https://img.alicdn.com/imgextra/i4/1804006046980628855/TB2Ytk9qB8lpuFjSspaXXXJKpXa_!!0-saturn_solar.jpg_220x220.jpg_.webp"
}]
